torchxlstm/__init__.py
torchxlstm/xlstm.py
torchxlstm-0.0.3.dist-info/LICENSE
torchxlstm-0.0.3.dist-info/METADATA
torchxlstm-0.0.3.dist-info/WHEEL
torchxlstm-0.0.3.dist-info/top_level.txt
torchxlstm-0.0.3.dist-info/RECORD
