Metadata-Version: 2.1
Name: torchxlstm
Version: 0.0.3
Summary: A pure pytorch implementation of xLSTM.
Author-email: Akaash Dash <akaash.dash@gmail.com>
Maintainer-email: Akaash Dash <akaash.dash@gmail.com>
Project-URL: Homepage, https://github.com/akaashdash/xlstm
Project-URL: Source, https://github.com/akaashdash/xlstm/
Keywords: xlstm,lstm,torch,pytorch
Classifier: Programming Language :: Python :: 3
Classifier: License :: OSI Approved :: MIT License
Classifier: Operating System :: OS Independent
Requires-Python: >=3
License-File: LICENSE
Requires-Dist: torch
